meta_notebook/__init__.py
meta_notebook/_modidx.py
meta_notebook/core.py
meta_notebook-0.0.3.dist-info/LICENSE
meta_notebook-0.0.3.dist-info/METADATA
meta_notebook-0.0.3.dist-info/WHEEL
meta_notebook-0.0.3.dist-info/entry_points.txt
meta_notebook-0.0.3.dist-info/top_level.txt
meta_notebook-0.0.3.dist-info/RECORD
