Metadata-Version: 2.1
Name: meta-notebook
Version: 0.0.3
Summary: Treat Jupyter notebooks as lego bricks and create something beautiful.
Home-page: https://github.com/radekosmulski/meta_notebook
Author: Radek Osmulski
Author-email: rosmulski@gmail.com
License: Apache Software License 2.0
Keywords: nbdev jupyter notebook python
Platform: UNKNOWN
Classifier: Development Status :: 4 - Beta
Classifier: Intended Audience :: Developers
Classifier: Natural Language :: English
Classifier: Programming Language :: Python :: 3.7
Classifier: Programming Language :: Python :: 3.8
Classifier: Programming Language :: Python :: 3.9
Classifier: Programming Language :: Python :: 3.10
Classifier: License :: OSI Approved :: Apache Software License
Requires-Python: >=3.7
License-File: LICENSE
Requires-Dist: execnb
Requires-Dist: fastcore
Provides-Extra: dev
